AUTHORS
CHANGELOG
MANIFEST.in
NEWS
README.txt
distribute_setup.py
install-rpm.sh
lgpl.txt
nosetests.1
patch.py
selftest.py
setup.cfg
setup.py
setup3lib.py
bin/nosetests
doc/Makefile
doc/api.rst
doc/conf.py
doc/contributing.rst
doc/developing.rst
doc/doc_tests
doc/docstring.py
doc/finding_tests.rst
doc/further_reading.rst
doc/index.html
doc/index.rst
doc/man.rst
doc/more_info.rst
doc/news.rst
doc/plugins.rst
doc/rtd-requirements.txt
doc/setuptools_integration.rst
doc/testing.rst
doc/testing_tools.rst
doc/usage.rst
doc/writing_tests.rst
doc/.static/nose.css
doc/.templates/index.html
doc/.templates/indexsidebar.html
doc/.templates/layout.html
doc/.templates/page.html
doc/api/commands.rst
doc/api/config.rst
doc/api/core.rst
doc/api/importer.rst
doc/api/inspector.rst
doc/api/loader.rst
doc/api/plugin_manager.rst
doc/api/proxy.rst
doc/api/result.rst
doc/api/selector.rst
doc/api/suite.rst
doc/api/test_cases.rst
doc/api/twistedtools.rst
doc/api/util.rst
doc/plugins/allmodules.rst
doc/plugins/attrib.rst
doc/plugins/builtin.rst
doc/plugins/capture.rst
doc/plugins/collect.rst
doc/plugins/cover.rst
doc/plugins/debug.rst
doc/plugins/deprecated.rst
doc/plugins/doctests.rst
doc/plugins/documenting.rst
doc/plugins/errorclasses.rst
doc/plugins/failuredetail.rst
doc/plugins/interface.rst
doc/plugins/isolate.rst
doc/plugins/logcapture.rst
doc/plugins/multiprocess.rst
doc/plugins/other.rst
doc/plugins/prof.rst
doc/plugins/skip.rst
doc/plugins/testid.rst
doc/plugins/testing.rst
doc/plugins/writing.rst
doc/plugins/xunit.rst
examples/attrib_plugin.py
examples/html_plugin/htmlplug.py
examples/html_plugin/setup.py
examples/plugin/plug.py
examples/plugin/setup.py
functional_tests/test_attribute_plugin.py
functional_tests/test_buggy_generators.py
functional_tests/test_cases.py
functional_tests/test_collector.py
functional_tests/test_commands.py
functional_tests/test_config_files.py
functional_tests/test_coverage_plugin.py
functional_tests/test_defaultpluginmanager.py
functional_tests/support/ep/Some_plugin.egg-info/PKG-INFO
functional_tests/support/ep/Some_plugin.egg-info/SOURCES.txt
functional_tests/support/ep/Some_plugin.egg-info/dependency_links.txt
functional_tests/support/ep/Some_plugin.egg-info/entry_points.txt
functional_tests/support/ep/Some_plugin.egg-info/top_level.txt
nose_for_sneeze.egg-info/PKG-INFO
nose_for_sneeze.egg-info/SOURCES.txt
nose_for_sneeze.egg-info/dependency_links.txt
nose_for_sneeze.egg-info/entry_points.txt
nose_for_sneeze.egg-info/not-zip-safe
nose_for_sneeze.egg-info/top_level.txt
