Metadata-Version: 1.1
Name: nose-for-sneeze
Version: 1.3.0
Summary: nose extends unittest to make testing easier
Home-page: http://readthedocs.org/docs/nose/
Author: Jason Pellerin
Author-email: jpellerin+nose@gmail.com
License: GNU LGPL
Keywords: test unittest doctest automatic discovery
Platform: UNKNOWN
Classifier: Development Status :: 5 - Production/Stable
Classifier: Intended Audience :: Developers
Classifier: License :: OSI Approved :: GNU Library or Lesser General Public License (LGPL)
Classifier: Natural Language :: English
Classifier: Operating System :: OS Independent
Classifier: Programming Language :: Python
Classifier: Programming Language :: Python :: 3
Classifier: Topic :: Software Development :: Testing
